relastii/__init__.py
relastii/dom.py
relastii/expr.py
relastii/mesh.py
relastii/relastii.cp310-win_amd64.pyd
relastii-0.1.5.data/data/README/README.md
relastii-0.1.5.data/data/licenses/APACHE2
relastii-0.1.5.data/data/licenses/MIT
relastii-0.1.5.dist-info/LICENSE
relastii-0.1.5.dist-info/METADATA
relastii-0.1.5.dist-info/WHEEL
relastii-0.1.5.dist-info/top_level.txt
relastii-0.1.5.dist-info/RECORD
